{
  "name": "TonSwap token list",
  "version": "0.0.1",
  "type": "TON",
  "keywords": [
    "tonswap",
    "tokens"
  ],
  "logo": "https://tonswap.com/img/logo.png",
  "url": "https://tonswap.com",
  "timestamp": "2020-12-14T18:56:35+0000",
  "tokens": [
    {
      "rootAddress": "0:4e632a56390f0dc9b644e0f94f64f89921fd4d588ae0002752b1059b0cbcf7e0",
      "name": "Ethereum",
      "symbol": "ETH",
      "decimals": 9,
      "config": {},
      "icon": "http://localhost:3000/img/exchange/eth.png"
    },
    {
      "rootAddress": "0:0daea83e6f5ff9b2d9dc6aef7190a7fdbd8accc476c0cd7ee39f15f3db74b851",
      "name": "Block-Chain.com",
      "symbol": "BC",
      "decimals": 9,
      "config": {},
      "icon": "https://raw.githubusercontent.com/trustwallet/assets/master/blockchains/ethereum/assets/0x2ecB13A8c458c379c4d9a7259e202De03c8F3D19/logo.png"
    }
  ]
}